LICENSE
README.md
setup.py
mathexpr/__init__.py
mathexpr.egg-info/PKG-INFO
mathexpr.egg-info/SOURCES.txt
mathexpr.egg-info/dependency_links.txt
mathexpr.egg-info/top_level.txt
mathlang/__init__.py