Metadata-Version: 2.1
Name: mathexpr
Version: 1.0.3
Summary: A library for parsing math strings
Home-page: https://github.com/professionsalincpp/MathParse
Author: griuc
Author-email: griguchaev@yandex.ru
License: MIT
Classifier: Programming Language :: Python :: 3
Classifier: License :: OSI Approved :: MIT License
Classifier: Operating System :: OS Independent
License-File: LICENSE
